Workbook

Sheet Entreprises
A1: Ville | B1: Catégorie (secteur) | C1: Nom de l'entreprise | D1: Produits / services offerts | E1: Prix (si disponible) | F1: Lien de géolocalisation (Google Maps) | G1: Site web (recherche Google) | H1: Note Google /5 | I1: Nb d'avis | J1: Avis des clients (synthèse) | K1: Téléphone
A2: Douala | B2: Restauration | C2: The Yard | D2: Restaurant-lounge, cuisine variée, cocktails, DJ | E2: Niveau Google : $$$ (cocktails jugés chers) | F2: Voir sur Google Maps | G2: Chercher le site web | H2: 4.4 | I2: 133 | J2: Cadre chic, service pro et DJ appréciés ; cuisine bonne mais prix élevés. | K2: +237 671 49 07 33
A3: Douala | B3: Restauration | C3: One Rooftop | D3: Restaurant, lounge-bar et club en rooftop ; cuisines internationales, dim sum, sushi | E3: Niveau Google : $$$$ (~40 € minimum le dîner selon un avis) | F3: Voir sur Google Maps | G3: Chercher le site web | H3: 4.3 | I3: 765 | J3: Décor raffiné, cocktails et finger-food salués ; très cher. | K3: +237 671 03 33 33
A4: Douala | B4: Restauration | C4: Piccola Venezia Restaurant | D4: Restaurant italien : pizzas, pâtes | E4: Non communiqué | F4: Voir sur Google Maps | G4: Chercher le site web | H4: 4.3 | I4: 318 | J4: Pizzas et pâtes très appréciées, personnel attentionné ; manque une terrasse. | K4: +237 699 93 17 21
A5: Douala | B5: Restauration | C5: La Fourchette | D5: Restaurant, bar, espace lounge ; cuisine européenne | E5: Niveau Google : non indiqué (jugé cher, vins onéreux) | F5: Voir sur Google Maps | G5: Chercher le site web | H5: 4.1 | I5: 478 | J5: Personnel pro, ambiance jazz ; peu de choix végétarien, prix élevés, parking limité. | K5: +237 699 92 64 66
A6: Douala | B6: Restauration | C6: VAULT CMR | D6: Restaurant lounge sur toit avec musique live, cocktails | E6: Non communiqué | F6: Voir sur Google Maps | G6: Chercher le site web | H6: 4.6 | I6: 68 | J6: Ambiance chic et calme, cocktails et plats bien notés. | K6: +237 675 12 48 70
A7: Douala | B7: Restauration | C7: Le Grilladin Restaurant | D7: Buffet à volonté de cuisine camerounaise, bar, karaoké | E7: Buffet dîner : 10 000 FCFA/personne (avis client) | F7: Voir sur Google Maps | G7: Chercher le site web | H7: 4 | I7: 823 | J7: Ambiance agréable et bon rapport prix ; qualité de la cuisine variable. | K7: +237 694 53 63 71
A8: Douala | B8: Restauration | C8: Maison H | D8: Café-restaurant, glacier, pâtes et desserts | E8: Niveau Google : non indiqué (jugé un peu cher) | F8: Voir sur Google Maps | G8: Chercher le site web | H8: 4.3 | I8: 3115 | J8: Cadre calme et élégant, pâtes et glaces très appréciées ; assez cher. | K8: +237 656 00 55 55
A9: Douala | B9: Restauration | C9: L'Ethnic Restaurant | D9: Cuisine africaine (Cameroun, Sénégal, Côte d'Ivoire), cocktails | E9: Niveau Google : $$$$ | F9: Voir sur Google Maps | G9: Chercher le site web | H9: 4.3 | I9: 177 | J9: Nourriture excellente, cadre soigné, restaurant tenu par une Camerounaise ; dress code. | K9: +237 671 25 91 54
A10: Douala | B10: Hôtellerie | C10: ONOMO Hotel Douala | D10: Hôtel, restaurant, bar, navette aéroport | E10: Chambre standard : ~135 €/nuit (un avis client) | F10: Voir sur Google Maps | G10: Chercher le site web | H10: 4.2 | I10: 1377 | J10: Service et restaurant salués ; quelques critiques sur l'entretien des chambres. | K10: +237 695 00 00 00
A11: Douala | B11: Hôtellerie | C11: Saffana Hotel | D11: Hôtel proche de l'aéroport, restaurant, navette | E11: Non communiqué | F11: Voir sur Google Maps | G11: Chercher le site web | H11: 3.5 | I11: 1005 | J11: Personnel accueillant, bien situé ; Wi-Fi et TV à améliorer. | K11: +237 659 31 00 34
A12: Douala | B12: Hôtellerie | C12: Hotel Akwa Palace Douala | D12: Hôtel historique, restaurant, bar, salles d'événements, piscine | E12: Non communiqué | F12: Voir sur Google Maps | G12: Chercher le site web | H12: 4.1 | I12: 3330 | J12: Accueil et service appréciés ; bâtiment et literie à moderniser. | K12: +237 233 42 26 01
A13: Douala | B13: Hôtellerie | C13: K Hotel Douala | D13: Hôtel, restaurant, bar-piscine, événements | E13: Non communiqué | F13: Voir sur Google Maps | G13: Chercher le site web | H13: 4.5 | I13: 928 | J13: Très bien noté (déco, service, ménage 2x/jour) ; quelques avis négatifs sur le management. | K13: +237 233 50 74 00
... A17: Douala | B17: Hôtellerie | C17: Hôtel JOANA | D17: Hôtel économique | E17: Chambres abordables (avis) | F17: Voir sur Google Maps | G17: Chercher le site web | H17: 3.5 | I17: 228 | J17: Propre, calme et bon marché ; quelques travaux restent à finir. | K17: +237 653 55 63 55
A18: Douala | B18: Banque & Finance | C18: Afriland First Bank Mboppi | D18: Banque : comptes, cartes, guichet | E18: Non communiqué | F18: Voir sur Google Maps | G18: Chercher le site web | H18: 4.1 | I18: 34 | J18: Agence facile à repérer, avis courts et positifs.
A19: Douala | B19: Banque & Finance | C19: Union Bank of Cameroon | D19: Banque : services bancaires courants | E19: Non communiqué | F19: Voir sur Google Maps | G19: Chercher le site web | H19: 4.4 | I19: 14 | J19: Service fluide et correct. | K19: +237 233 42 25 08
A20: Douala | B20: Banque & Finance | C20: AFG Bank Cameroun (Siège social) | D20: Banque : comptes, cartes, DAB | E20: Non communiqué | F20: Voir sur Google Maps | G20: Chercher le site web | H20: 3.6 | I20: 38 | J20: Personnel bilingue et gamme de comptes ; avis partagés sur la lenteur. | K20: +237 233 50 99 00
A21: Douala | B21: Banque & Finance | C21: Atlantic Bank Ndogbong | D21: Banque : services bancaires courants | E21: Non communiqué | F21: Voir sur Google Maps | G21: Chercher le site web | H21: 3.1 | I21: 37 | J21: Accueil jugé médiocre par plusieurs clients. | K21: +237 691 92 75 55
A22: Douala | B22: Banque & Finance | C22: UBA Cameroon Head Office | D22: Banque : siège, comptes, transferts, cartes | E22: Non communiqué | F22: Voir sur Google Maps | G22: Chercher le site web | H22: 3.9 | I22: 100 | J22: Équipe réactive mais files d'attente longues. | K22: +237 233 50 67 82
A23: Douala | B23: Banque & Finance | C23: SCB Cameroun (Attijariwafa Bank) | D23: Banque : comptes, DAB (réseau Total) | E23: Non communiqué | F23: Voir sur Google Maps | G23: Chercher le site web | H23: 3.2 | I23: 35 | J23: Réseau de DAB apprécié ; service client critiqué. | K23: +237 233 43 53 00
A24: Douala | B24: Banque & Finance | C24: SGC Bank Bonanjo | D24: Banque : services bancaires courants | E24: Non communiqué | F24: Voir sur Google Maps | G24: Chercher le site web | H24: 4 | I24: 57 | J24: Bons locaux, service perfectible. | K24: +237 233 50 18 18
A25: Douala | B25: Banque & Finance | C25: Banque Atlantique Joss | D25: Banque : services bancaires courants | E25: Non communiqué | F25: Voir sur Google Maps | G25: Chercher le site web | H25: 3.7 | I25: 9 | J25: Service rapide pour certains ; bâtiment vieillissant. | K25: +237 233 42 10 66
A26: Douala | B26: Pharmacie | C26: Pharmacie de Douala | D26: Pharmacie ouverte 24h/24 | E26: Non communiqué | F26: Voir sur Google Maps | G26: Chercher le site web | H26: 4.8 | I26: 6 | J26: Peu d'avis, note élevée. | K26: +237 698 00 26 69
A27: Douala | B27: Pharmacie | C27: Pharmacy Kotto | D27: Pharmacie, large gamme de produits médicaux | E27: Non communiqué | F27: Voir sur Google Maps | G27: Chercher le site web | H27: 4 | I27: 68 | J27: Grande pharmacie bien fournie ; un client la dit fermée un jour. | K27: +237 697 04 10 56
A28: Douala | B28: Pharmacie | C28: Pharmacie de Logpom | D28: Pharmacie de garde 24h/24 | E28: Non communiqué | F28: Voir sur Google Maps | G28: Chercher le site web | H28: 3.7 | I28: 39 | J28: Personnel accueillant et compétent, utile la nuit. | K28: +237 233 77 39 13
A29: Douala | B29: Pharmacie | C29: Pharmacie de l'Alliance | D29: Pharmacie, médicaments | E29: Non communiqué | F29: Voir sur Google Maps | G29: Chercher le site web | H29: 4.1 | I29: 54 | J29: Personnel compétent, bons conseils. | K29: +237 233 42 99 15
A30: Douala | B30: Pharmacie | C30: Pharmacie du Plateau | D30: Pharmacie 24h/24 à Bonapriso | E30: Non communiqué | F30: Voir sur Google Maps | G30: Chercher le site web | H30: 4.2 | I30: 33 | J30: Bien organisée, service rapide et aimable. | K30: +237 679 70 46 26
... A111: Douala | B111: BTP & matériaux de construction | C111: TC BTP SARL | D111: Entreprise de BTP et finitions | E111: Non communiqué | F111: Voir sur Google Maps | G111: Chercher le site web | H111: 5 | I111: 5 | J111: Respect des délais, finitions de qualité. | K111: +237 699 63 38 82
A112: Douala | B112: BTP & matériaux de construction | C112: Royal Construction Cameroun | D112: Tôles bac, tuiles ondulées, fournitures de construction | E112: Non communiqué | F112: Voir sur Google Maps | G112: Chercher le site web | H112: 4.5 | I112: 2 | J112: Produits et service de très bonne qualité.
A113: Douala | B113: BTP & matériaux de construction | C113: COGENI Bonamoussadi | D113: Quincaillerie et matériaux en gros | E113: Prix compétitifs (avis) | F113: Voir sur Google Maps | G113: Chercher le site web | H113: 3.7 | I113: 63 | J113: Prix intéressants ; un avis critique sur l'accueil. | K113: +237 671 34 04 31
A114: Douala | B114: Juridique (avocats / notaires) | C114: Cabinet d'Avocats Nguéé & Associés | D114: Cabinet d'avocats | E114: Non communiqué | F114: Voir sur Google Maps | G114: Chercher le site web | H114: 4.7 | I114: 36 | J114: Équipe jeune, dynamique et à l'écoute. | K114: +237 242 00 96 12
A115: Douala | B115: Juridique (avocats / notaires) | C115: Bitanga & Partners Law Firm | D115: Cabinet d'avocats : droit des affaires, fiscal | E115: Non communiqué | F115: Voir sur Google Maps | G115: Chercher le site web | H115: 4.7 | I115: 56 | J115: Approche moderne et transparente ; certains dossiers longs. | K115: +237 620 11 98 77
A116: Douala | B116: Juridique (avocats / notaires) | C116: 4M Legal and Tax | D116: Conseil juridique et fiscal, création d'entreprise | E116: Non communiqué | F116: Voir sur Google Maps | G116: Chercher le site web | H116: 4.9 | I116: 54 | J116: Très bien noté : professionnalisme et suivi étape par étape. | K116: +237 698 10 53 19
A117: Douala | B117: Juridique (avocats / notaires) | C117: Cabinet Notaire (Me Eboutou) | D117: Étude notariale | E117: Non communiqué | F117: Voir sur Google Maps | G117: Chercher le site web | H117: 3.5 | I117: 2 | J117: Peu d'avis. | K117: +237 233 43 16 62
A118: Douala | B118: Juridique (avocats / notaires) | C118: Maaron Law Firm | D118: Cabinet juridique | E118: Non communiqué | F118: Voir sur Google Maps | G118: Chercher le site web | H118: 5 | I118: 1 | J118: Un seul avis. | K118: +237 680 35 12 25
A119: Douala | B119: Communication & impression | C119: Group M.A.O – Agence de communication | D119: Gestion de pages/réseaux sociaux, monétisation | E119: Non communiqué | F119: Voir sur Google Maps | G119: Chercher le site web | H119: 5 | I119: 8 | J119: Clients satisfaits de la gestion de leurs comptes. | K119: +237 675 18 74 31
A120: Douala | B120: Communication & impression | C120: Easyprinting Cameroon | D120: Impression, objets publicitaires, diplômes et attestations | E120: Non communiqué | F120: Voir sur Google Maps | G120: Chercher le site web | H120: 4.3 | I120: 12 | J120: Impression de qualité, clients satisfaits. | K120: +237 697 80 86 50
A121: Douala | B121: Communication & impression | C121: Jerry Kamgang | D121: Formations en marketing digital (Facebook, WhatsApp) | E121: Non communiqué | F121: Voir sur Google Maps | G121: Chercher le site web | H121: 4.8 | I121: 281 | J121: Formation bien structurée et très appréciée ; un avis déçu. | K121: +237 696 34 30 36
A122: Douala | B122: Communication & impression | C122: AJC Graphic SARL | D122: Imprimerie, conception graphique | E122: Non communiqué | F122: Voir sur Google Maps | G122: Chercher le site web | H122: 4 | I122: 1 | J122: Un seul avis. | K122: +237 699 91 25 89
A123: Douala | B123: Communication & impression | C123: Digital Print Cameroun | D123: Impression numérique | E123: Non communiqué | F123: Voir sur Google Maps | G123: Chercher le site web | H123: 4.7 | I123: 6 | J123: Équipe jeune, dynamique et professionnelle. | K123: +237 658 90 00 00
A124: Douala | B124: Sport & loisirs | C124: O'Sport | D124: Salle de sport, coaching, complexe sportif | E124: Non communiqué (jugé cher par un membre) | F124: Voir sur Google Maps | G124: Chercher le site web | H124: 4.7 | I124: 676 | J124: Grande salle, coachs nombreux ; matériel vieillissant selon un avis. | K124: +237 699 24 43 01
... A139: Yaoundé | B139: Banque & Finance | C139: SGBC (Société Générale Cameroun) – Agence Hippodrome | D139: Banque : comptes, DAB | E139: Non communiqué | F139: Voir sur Google Maps | G139: Chercher le site web | H139: 3.4 | I139: 26 | J139: Bonne localisation ; horaires non respectés et problèmes de virements. | K139: +237 233 50 18 18
A140: Yaoundé | B140: Banque & Finance | C140: Atlantic Bank Yaoundé | D140: Banque : siège, avenue de Gaulle | E140: Non communiqué | F140: Voir sur Google Maps | G140: Chercher le site web | H140: 3.6 | I140: 28 | J140: Files courtes, service rapide ; pannes de système.
A141: Yaoundé | B141: Banque & Finance | C141: Union Bank of Cameroun (Yaoundé) | D141: Banque : services courants | E141: Non communiqué | F141: Voir sur Google Maps | G141: Chercher le site web | H141: 3 | I141: 25 | J141: Service rapide et grand parking, peu d'affluence. | K141: +237 699 17 42 62
A142: Yaoundé | B142: Banque & Finance | C142: SGBC Bank & ATM – Avenue de Gaulle | D142: Banque : comptes, DAB | E142: Non communiqué | F142: Voir sur Google Maps | G142: Chercher le site web | H142: 3.6 | I142: 43 | J142: Banque réputée, marge d'amélioration. | K142: +237 233 50 18 18
A143: Yaoundé | B143: Banque & Finance | C143: UBA Cameroun (Yaoundé) | D143: Banque : comptes, transferts, banque en ligne | E143: Non communiqué | F143: Voir sur Google Maps | G143: Chercher le site web | H143: 3.4 | I143: 70 | J143: Bons services en ligne, mais longues attentes. | K143: +237 233 43 36 89
A144: Yaoundé | B144: Pharmacie | C144: Pharmacie Des Nations | D144: Pharmacie 24h/24, produits professionnels | E144: Non communiqué | F144: Voir sur Google Maps | G144: Chercher le site web | H144: 3.9 | I144: 37 | J144: Bien approvisionnée, accueil chaleureux. | K144: +237 222 20 93 58
A145: Yaoundé | B145: Pharmacie | C145: Star Pharmacy | D145: Pharmacie (24h/24 annoncé) | E145: Non communiqué | F145: Voir sur Google Maps | G145: Chercher le site web | H145: 3.5 | I145: 4 | J145: Un client n'a pas trouvé l'adresse : à vérifier avant déplacement.
A146: Yaoundé | B146: Pharmacie | C146: Pharmacie Bleue | D146: Pharmacie près de l'hôpital général de Ngousso | E146: Non communiqué | F146: Voir sur Google Maps | G146: Chercher le site web | H146: 3.7 | I146: 36 | J146: Facile à trouver, avis courts positifs. | K146: +237 698 87 08 01
A147: Yaoundé | B147: Pharmacie | C147: Heliana's Pharmacy | D147: Pharmacie | E147: Non communiqué | F147: Voir sur Google Maps | G147: Chercher le site web | H147: 4.4 | I147: 5 | J147: Équipe et service très appréciés.
A148: Yaoundé | B148: Pharmacie | C148: Pharmacie Maelys | D148: Pharmacie | E148: Non communiqué | F148: Voir sur Google Maps | G148: Chercher le site web | I148: 0 | J148: Pas encore d'avis.
A149: Yaoundé | B149: Commerce & Grande distribution | C149: Dovv Bastos Supermarket | D149: Supermarché : produits locaux, boulangerie, plats à emporter | E149: Non communiqué (certains prix jugés élevés) | F149: Voir sur Google Maps | G149: Chercher le site web | H149: 3.7 | I149: 2274 | J149: Bon choix et prix corrects ; bouteilles consignées. | K149: +237 690 12 96 42
A150: Yaoundé | B150: Commerce & Grande distribution | C150: Carrefour Playce | D150: Supermarché Carrefour dans le mall Playce | E150: Prix abordables (avis) | F150: Voir sur Google Maps | G150: Chercher le site web | H150: 4.3 | I150: 1387 | J150: Bien organisé, large gamme, produits locaux et frais.
A151: Yaoundé | B151: Commerce & Grande distribution | C151: PlaYce Yaoundé | D151: Centre commercial : boutiques, restaurants, aire de jeux, parking | E151: Non communiqué | F151: Voir sur Google Maps | G151: Chercher le site web | H151: 4.4 | I151: 1844 | J151: Propre, moderne, idéal en famille.
A152: Yaoundé | B152: Commerce & Grande distribution | C152: Carrefour Market EKIE | D152: Supermarché ouvert 24h/24 | E152: Prix raisonnables (avis) | F152: Voir sur Google Maps | G152: Chercher le site web | H152: 4.1 | I152: 1961 | J152: Bien organisé, personnel aimable, grand parking. | K152: +237 695 60 62 27
A153: Yaoundé | B153: Commerce & Grande distribution | C153: Santa Lucia Mvan | D153: Supermarché 24h/24, boulangerie, pâtisserie, restauration rapide | E153: Prix corrects (avis) | F153: Voir sur Google Maps | G153: Chercher le site web | H153: 3.8 | I153: 3731 | J153: Grand choix, pain très apprécié ; attention aux pickpockets. | K153: +237 665 26 30 74
A154: Yaoundé | B154: Santé (cliniques / hôpitaux) | C154: Medical Center Le Jourdain | D154: Clinique, laboratoire, maternité, kinésithérapie | E154: Jugé cher (avis) | F154: Voir sur Google Maps | G154: Chercher le site web | H154: 3.6 | I154: 123 | J154: Avis très partagés : bon plateau technique, mais attente et accueil critiqués. | K154: +237 656 34 01 65
A155: Yaoundé | B155: Santé (cliniques / hôpitaux) | C155: Surgical Medical Center St Alphonse | D155: Centre médico-chirurgical, urgences | E155: Non communiqué | F155: Voir sur Google Maps | G155: Chercher le site web | H155: 4.9 | I155: 37 | J155: Excellente réputation : personnel pro, accueil chaleureux. | K155: +237 672 50 13 29
A156: Yaoundé | B156: Santé (cliniques / hôpitaux) | C156: Hôpital Bethesda | D156: Hôpital privé | E156: Non communiqué | F156: Voir sur Google Maps | G156: Chercher le site web | H156: 3.9 | I156: 29 | J156: Longues attentes signalées. | K156: +237 242 69 91 40
A157: Yaoundé | B157: Santé (cliniques / hôpitaux) | C157: Polyclinique Groupe Médical St-Hilaire | D157: Polyclinique à Bastos | E157: Prix élevés (avis) | F157: Voir sur Google Maps | G157: Chercher le site web | H157: 2.8 | I157: 28 | J157: Accueil et attente critiqués ; prix jugés élevés. | K157: +237 679 05 04 04
A158: Yaoundé | B158: Santé (cliniques / hôpitaux) | C158: Hôpital de District de Biyem-Assi | D158: Hôpital public de district | E158: Non communiqué | F158: Voir sur Google Maps | G158: Chercher le site web | H158: 3.5 | I158: 55 | J158: Propre et bien situé pour certains ; hygiène critiquée par d'autres. | K158: +237 222 31 30 77
A159: Yaoundé | B159: Éducation & Formation | C159: Université Saint Jean-Paul II | D159: Université catholique privée | E159: Non communiqué | F159: Voir sur Google Maps | G159: Chercher le site web | H159: 4.1 | I159: 77 | J159: Bon cadre d'étude ; entretien parfois insuffisant. | K159: +237 691 31 96 62
A160: Yaoundé | B160: Éducation & Formation | C160: École normale supérieure de Yaoundé | D160: Formation des enseignants (ENS) | E160: Non communiqué | F160: Voir sur Google Maps | G160: Chercher le site web | H160: 3.9 | I160: 218 | J160: Cadre calme, institution ancienne et respectée. | K160: +237 690 24 52 37
A161: Yaoundé | B161: Éducation & Formation | C161: Université Catholique d'Afrique Centrale (UCAC) | D161: Université catholique (jésuites) | E161: Non communiqué | F161: Voir sur Google Maps | G161: Chercher le site web | H161: 4.1 | I161: 466 | J161: Belle architecture, cadre académique solide. | K161: +237 222 23 74 00
A162: Yaoundé | B162: Éducation & Formation | C162: Université de Yaoundé 1 (Ngoa Ekelle) | D162: Université publique bilingue | E162: Non communiqué | F162: Voir sur Google Maps | G162: Chercher le site web | H162: 3.8 | I162: 173 | J162: Grande université de référence, très fréquentée. | K162: +237 691 88 01 90
A163: Yaoundé | B163: Éducation & Formation | C163: École nationale supérieure polytechnique (ENSPY) | D163: Grande école d'ingénieurs | E163: Non communiqué | F163: Voir sur Google Maps | G163: Chercher le site web | H163: 4.1 | I163: 856 | J163: La plus ancienne école d'ingénieurs du pays, concours très sélectif.
A164: Yaoundé | B164: Automobile (garages) | C164: Souley Garage Auto | D164: Mécanique, électricité auto, tôlerie, peinture | E164: Non communiqué | F164: Voir sur Google Maps | G164: Chercher le site web | H164: 5 | I164: 3 | J164: Très professionnel ; deux garages sur le même site, bien vérifier l'enseigne. | K164: +237 656 92 99 21
A165: Yaoundé | B165: Automobile (garages) | C165: Top Garage Automobile | D165: Garage automobile, suivi après-vente | E165: Non communiqué | F165: Voir sur Google Maps | G165: Chercher le site web | H165: 4.9 | I165: 8 | J165: Fiable et honnête, travail bien fait. | K165: +237 658 93 21 22
A166: Yaoundé | B166: Automobile (garages) | C166: 3S Motors (Yaoundé) | D166: Garage automobile | E166: Tarifs équitables et transparents (avis) | F166: Voir sur Google Maps | G166: Chercher le site web | H166: 4.8 | I166: 69 | J166: Équipe sérieuse, délais respectés, bonne communication.
A167: Yaoundé | B167: Automobile (garages) | C167: Garage BMW | D167: Garage automobile | E167: Non communiqué | F167: Voir sur Google Maps | G167: Chercher le site web | H167: 5 | I167: 2 | J167: Peu d'avis. | K167: +237 677 37 24 88
A168: Yaoundé | B168: Automobile (garages) | C168: Garage Auto Service P.A | D168: Mécanique automobile (Mercedes notamment) | E168: Non communiqué | F168: Voir sur Google Maps | G168: Chercher le site web | H168: 4.8 | I168: 6 | J168: Diagnostic rapide et efficace. | K168: +237 655 81 44 48
A169: Yaoundé | B169: Voyage & Transport | C169: Agence Française de Voyages (AFV) | D169: Billets d'avion, voyages sur mesure | E169: Renseignements gratuits (avis) | F169: Voir sur Google Maps | G169: Chercher le site web | H169: 4.3 | I169: 52 | J169: Professionnelle, conseils et suivi très appréciés. | K169: +237 677 93 78 22
A170: Yaoundé | B170: Voyage & Transport | C170: Moabi Travels – American Express | D170: Agence de voyages, billetterie | E170: Non communiqué | F170: Voir sur Google Maps | G170: Chercher le site web | H170: 4.1 | I170: 43 | J170: Personnel flexible et à l'écoute. | K170: +237 673 98 12 51
A171: Yaoundé | B171: Voyage & Transport | C171: SOFITOUL SA – Agence de voyages | D171: Billets d'avion, circuits, location de voitures, change, événementiel | E171: Non communiqué | F171: Voir sur Google Maps | G171: Chercher le site web | H171: 4.3 | I171: 26 | J171: Agence réputée ; un avis négatif. | K171: +237 697 78 81 93
A172: Yaoundé | B172: Voyage & Transport | C172: Men Travel (Yaoundé) | D172: Transport interurbain en bus (classes VIP/Business) | E172: Kribi–Yaoundé : 6 000 FCFA (avis) ; sandwich Business ~10 000 FCFA | F172: Voir sur Google Maps | G172: Chercher le site web | H172: 3.4 | I172: 778 | J172: Beaux bus mais retards et service client très critiqués. | K172: +237 653 67 74 43
A173: Yaoundé | B173: Voyage & Transport | C173: Finexs Voyages (Mvan) | D173: Transport Douala–Yaoundé, colis/courrier avec suivi | E173: Non communiqué | F173: Voir sur Google Maps | G173: Chercher le site web | H173: 3.8 | I173: 6210 | J173: Très populaire, bien organisé ; attentes à l'embarquement. | K173: +237 696 94 31 31
A174: Yaoundé | B174: Beauté & Bien-être | C174: Institut de Beauté GLADSTONE (Yaoundé) | D174: Coiffure, barbier, ongles, soins visage, massage, hammam | E174: Coupe femme ~15 000 FCFA (avis) ; haut de gamme | F174: Voir sur Google Maps | G174: Chercher le site web | H174: 4.7 | I174: 595 | J174: Qualité et professionnalisme très salués. | K174: +237 620 11 11 11
A175: Yaoundé | B175: Beauté & Bien-être | C175: Monsieur Rasage Hair Cut | D175: Coiffure mixte, soins visage, manucure, hammam, massage | E175: Non communiqué | F175: Voir sur Google Maps | G175: Chercher le site web | H175: 5 | I175: 1 | J175: Un avis, très positif. | K175: +237 640 94 09 35
A176: Yaoundé | B176: Beauté & Bien-être | C176: Dorcas Beauty Salon | D176: Salon de coiffure | E176: Non communiqué | F176: Voir sur Google Maps | G176: Chercher le site web | I176: 0 | J176: Pas encore d'avis. | K176: +237 676 52 88 00
A177: Yaoundé | B177: Beauté & Bien-être | C177: Atelier Beauté | D177: Coiffure, ongles, soins | E177: Jugé cher (avis) | F177: Voir sur Google Maps | G177: Chercher le site web | H177: 4.2 | I177: 20 | J177: Cadre propre et climatisé ; avis contrasté sur les ongles. | K177: +237 657 00 94 69
A178: Yaoundé | B178: Beauté & Bien-être | C178: Prestige Beauty Mix and Spa | D178: Salon mixte et spa | E178: Non communiqué | F178: Voir sur Google Maps | G178: Chercher le site web | H178: 5 | I178: 7 | J178: Accueil chaleureux, équipe pro, très propre. | K178: +237 653 53 01 84
A179: Yaoundé | B179: Assurance | C179: SAAR-VIE Assurances | D179: Assurances vie et non-vie | E179: Non communiqué | F179: Voir sur Google Maps | G179: Chercher le site web | H179: 4 | I179: 50 | J179: Service rapide et efficace. | K179: +237 697 96 75 46
A180: Yaoundé | B180: Assurance | C180: NSIA Assurances – Espace direct Yaoundé 1 | D180: Assurances santé, auto, habitation | E180: Non communiqué | F180: Voir sur Google Maps | G180: Chercher le site web | H180: 3.7 | I180: 46 | J180: Bonne orientation ; remboursements lents. | K180: +237 242 07 23 71
A181: Yaoundé | B181: Assurance | C181: AXA Assurance – Hippodrome | D181: Assurance voyage (Schengen), auto, habitation, entreprise | E181: Non communiqué | F181: Voir sur Google Maps | G181: Chercher le site web | H181: 3.7 | I181: 163 | J181: Reconnue pour l'assurance voyage ; lenteur due au réseau. | K181: +237 222 21 51 80
A182: Yaoundé | B182: Assurance | C182: Ascoma Cameroun – Agence de Yaoundé | D182: Courtage et assurances | E182: Non communiqué | F182: Voir sur Google Maps | G182: Chercher le site web | H182: 3.8 | I182: 89 | J182: Avis contrastés sur les remboursements. | K182: +237 222 21 51 80
A183: Yaoundé | B183: Immobilier | C183: LM Platinum Estates | D183: Vente de terrains, agence immobilière sécurisée | E183: Prix compétitifs (avis) | F183: Voir sur Google Maps | G183: Chercher le site web | H183: 4.9 | I183: 39 | J183: Très professionnelle, achats de terrains sécurisés. | K183: +237 692 85 05 84
A184: Yaoundé | B184: Immobilier | C184: Yaoundé Immobilier | D184: Agence immobilière : location, vente | E184: Non communiqué | F184: Voir sur Google Maps | G184: Chercher le site web | H184: 4.8 | I184: 55 | J184: Service client efficace et apprécié. | K184: +237 672 98 24 84
A185: Yaoundé | B185: Immobilier | C185: Les Experts de l'Immobilier 237 | D185: Services immobiliers | E185: Non communiqué | F185: Voir sur Google Maps | G185: Chercher le site web | H185: 4.9 | I185: 7 | J185: Très professionnels et fiables. | K185: +237 678 47 56 44
A186: Yaoundé | B186: Immobilier | C186: Galaxie Immobilier | D186: Vente de terrains et villas, location (Yaoundé/Douala) | E186: Non communiqué | F186: Voir sur Google Maps | G186: Chercher le site web | H186: 4.1 | I186: 34 | J186: Clients satisfaits de ventes et locations. | K186: +237 695 39 39 39
A187: Yaoundé | B187: Immobilier | C187: Mav SARL | D187: Gestion, location et vente de biens | E187: Non communiqué | F187: Voir sur Google Maps | G187: Chercher le site web | H187: 4 | I187: 38 | J187: Avis partagés : efficace mais réponses parfois lentes. | K187: +237 694 63 30 02
A188: Yaoundé | B188: Télécoms | C188: Boutique Orange Simbock | D188: Boutique opérateur Orange | E188: Non communiqué | F188: Voir sur Google Maps | G188: Chercher le site web | H188: 5 | I188: 1 | J188: Un seul avis. | K188: +237 233 41 00 00
A189: Yaoundé | B189: Télécoms | C189: Boutique Orange Nkomo | D189: Boutique opérateur Orange | E189: Non communiqué | F189: Voir sur Google Maps | G189: Chercher le site web | H189: 3 | I189: 2 | J189: Accueil compétent, avis partagés. | K189: +237 233 41 00 00
A190: Yaoundé | B190: Télécoms | C190: MTN Cameroun (Yaoundé) | D190: Agence MTN : SIM, data, box internet, Mobile Money | E190: Non communiqué | F190: Voir sur Google Maps | G190: Chercher le site web | H190: 3 | I190: 13 | J190: Bien située ; attente et litiges signalés.
A191: Yaoundé | B191: Télécoms | C191: Boutique Orange Bastos | D191: Boutique opérateur : SIM, eSIM | E191: Non communiqué | F191: Voir sur Google Maps | G191: Chercher le site web | H191: 3.7 | I191: 202 | J191: Très fréquentée, attente ; eSIM rapide selon certains. | K191: +237 233 41 00 00
A192: Yaoundé | B192: Télécoms | C192: Boutique Orange Colombia | D192: Boutique opérateur Orange | E192: Non communiqué | F192: Voir sur Google Maps | G192: Chercher le site web | H192: 4 | I192: 2 | J192: Très peu d'avis. | K192: +237 233 41 00 00
A193: Yaoundé | B193: Restauration rapide & boulangerie | C193: My Popeyes Pastry | D193: Pâtisserie, glaces, salon de thé | E193: Niveau Google : $$$ | F193: Voir sur Google Maps | G193: Chercher le site web | H193: 4.3 | I193: 50 | J193: Glaces onctueuses, cadre agréable ; salé moyen. | K193: +237 652 33 54 54
A194: Yaoundé | B194: Restauration rapide & boulangerie | C194: MyPopeyes | D194: Restauration rapide : poulet frit, kebabs, cuisine libanaise | E194: Bon rapport qualité-prix (avis) | F194: Voir sur Google Maps | G194: Chercher le site web | H194: 4.3 | I194: 16 | J194: Kebabs et poulet frit appréciés ; service parfois lent.
A195: Yaoundé | B195: Restauration rapide & boulangerie | C195: O'Good Food | D195: Restaurant américain, espace enfants | E195: Prix abordables (avis) | F195: Voir sur Google Maps | G195: Chercher le site web | H195: 4 | I195: 197 | J195: Propre, service attentif ; plats parfois indisponibles. | K195: +237 658 58 58 47
A196: Yaoundé | B196: Restauration rapide & boulangerie | C196: B-Delight | D196: Fast-food : burgers, wings, pizzas, porc grillé | E196: Non communiqué | F196: Voir sur Google Maps | G196: Chercher le site web | H196: 4.3 | I196: 19 | J196: Cuisine savoureuse, décor soigné. | K196: +237 655 16 20 26
A197: Yaoundé | B197: Restauration rapide & boulangerie | C197: La Croissanterie (Nlongkak) | D197: Croissanterie, sandwichs, jus, gâteaux | E197: Croissant/pain au chocolat ~800–1 000 FCFA (avis) | F197: Voir sur Google Maps | G197: Chercher le site web | H197: 4.3 | I197: 3 | J197: Viennoiseries excellentes, espace restreint. | K197: +237 690 31 21 98
...

Sheet Synthèse
A1: Nombre d'entreprises par ville et catégorie
A3: Catégorie | B3: Douala | C3: Yaoundé | D3: Bafoussam | E3: Total
A4: Restauration | B4: =COUNTIFS(Entreprises!$A$2:$A$315,B$3,Entreprises!$B$2:$B$315,$A4) -> 8 | C4: =COUNTIFS(Entreprises!$A$2:$A$315,C$3,Entreprises!$B$2:$B$315,$A4) -> 5 | D4: =COUNTIFS(Entreprises!$A$2:$A$315,D$3,Entreprises!$B$2:$B$315,$A4) -> 5 | E4: =SUM(B4:D4) -> 18
A5: Hôtellerie | B5: =COUNTIFS(Entreprises!$A$2:$A$315,B$3,Entreprises!$B$2:$B$315,$A5) -> 8 | C5: =COUNTIFS(Entreprises!$A$2:$A$315,C$3,Entreprises!$B$2:$B$315,$A5) -> 5 | D5: =COUNTIFS(Entreprises!$A$2:$A$315,D$3,Entreprises!$B$2:$B$315,$A5) -> 5 | E5: =SUM(B5:D5) -> 18
A6: Banque & Finance | B6: =COUNTIFS(Entreprises!$A$2:$A$315,B$3,Entreprises!$B$2:$B$315,$A6) -> 8 | C6: =COUNTIFS(Entreprises!$A$2:$A$315,C$3,Entreprises!$B$2:$B$315,$A6) -> 5 | D6: =COUNTIFS(Entreprises!$A$2:$A$315,D$3,Entreprises!$B$2:$B$315,$A6) -> 5 | E6: =SUM(B6:D6) -> 18
A7: Pharmacie | B7: =COUNTIFS(Entreprises!$A$2:$A$315,B$3,Entreprises!$B$2:$B$315,$A7) -> 8 | C7: =COUNTIFS(Entreprises!$A$2:$A$315,C$3,Entreprises!$B$2:$B$315,$A7) -> 5 | D7: =COUNTIFS(Entreprises!$A$2:$A$315,D$3,Entreprises!$B$2:$B$315,$A7) -> 5 | E7: =SUM(B7:D7) -> 18
A8: Commerce & Grande distribution | B8: =COUNTIFS(Entreprises!$A$2:$A$315,B$3,Entreprises!$B$2:$B$315,$A8) -> 8 | C8: =COUNTIFS(Entreprises!$A$2:$A$315,C$3,Entreprises!$B$2:$B$315,$A8) -> 5 | D8: =COUNTIFS(Entreprises!$A$2:$A$315,D$3,Entreprises!$B$2:$B$315,$A8) -> 5 | E8: =SUM(B8:D8) -> 18
A9: Santé (cliniques / hôpitaux) | B9: =COUNTIFS(Entreprises!$A$2:$A$315,B$3,Entreprises!$B$2:$B$315,$A9) -> 8 | C9: =COUNTIFS(Entreprises!$A$2:$A$315,C$3,Entreprises!$B$2:$B$315,$A9) -> 5 | D9: =COUNTIFS(Entreprises!$A$2:$A$315,D$3,Entreprises!$B$2:$B$315,$A9) -> 5 | E9: =SUM(B9:D9) -> 18
A10: Éducation & Formation | B10: =COUNTIFS(Entreprises!$A$2:$A$315,B$3,Entreprises!$B$2:$B$315,$A10) -> 8 | C10: =COUNTIFS(Entreprises!$A$2:$A$315,C$3,Entreprises!$B$2:$B$315,$A10) -> 5 | D10: =COUNTIFS(Entreprises!$A$2:$A$315,D$3,Entreprises!$B$2:$B$315,$A10) -> 5 | E10: =SUM(B10:D10) -> 18
A11: Automobile (garages) | B11: =COUNTIFS(Entreprises!$A$2:$A$315,B$3,Entreprises!$B$2:$B$315,$A11) -> 8 | C11: =COUNTIFS(Entreprises!$A$2:$A$315,C$3,Entreprises!$B$2:$B$315,$A11) -> 5 | D11: =COUNTIFS(Entreprises!$A$2:$A$315,D$3,Entreprises!$B$2:$B$315,$A11) -> 5 | E11: =SUM(B11:D11) -> 18
A12: Voyage & Transport | B12: =COUNTIFS(Entreprises!$A$2:$A$315,B$3,Entreprises!$B$2:$B$315,$A12) -> 8 | C12: =COUNTIFS(Entreprises!$A$2:$A$315,C$3,Entreprises!$B$2:$B$315,$A12) -> 5 | D12: =COUNTIFS(Entreprises!$A$2:$A$315,D$3,Entreprises!$B$2:$B$315,$A12) -> 5 | E12: =SUM(B12:D12) -> 18
A13: Beauté & Bien-être | B13: =COUNTIFS(Entreprises!$A$2:$A$315,B$3,Entreprises!$B$2:$B$315,$A13) -> 8 | C13: =COUNTIFS(Entreprises!$A$2:$A$315,C$3,Entreprises!$B$2:$B$315,$A13) -> 5 | D13: =COUNTIFS(Entreprises!$A$2:$A$315,D$3,Entreprises!$B$2:$B$315,$A13) -> 5 | E13: =SUM(B13:D13) -> 18
A14: Assurance | B14: =COUNTIFS(Entreprises!$A$2:$A$315,B$3,Entreprises!$B$2:$B$315,$A14) -> 5 | C14: =COUNTIFS(Entreprises!$A$2:$A$315,C$3,Entreprises!$B$2:$B$315,$A14) -> 4 | D14: =COUNTIFS(Entreprises!$A$2:$A$315,D$3,Entreprises!$B$2:$B$315,$A14) -> 5 | E14: =SUM(B14:D14) -> 14
A15: Immobilier | B15: =COUNTIFS(Entreprises!$A$2:$A$315,B$3,Entreprises!$B$2:$B$315,$A15) -> 5 | C15: =COUNTIFS(Entreprises!$A$2:$A$315,C$3,Entreprises!$B$2:$B$315,$A15) -> 5 | D15: =COUNTIFS(Entreprises!$A$2:$A$315,D$3,Entreprises!$B$2:$B$315,$A15) -> 3 | E15: =SUM(B15:D15) -> 13
... A23: Sport & loisirs | B23: =COUNTIFS(Entreprises!$A$2:$A$315,B$3,Entreprises!$B$2:$B$315,$A23) -> 5 | C23: =COUNTIFS(Entreprises!$A$2:$A$315,C$3,Entreprises!$B$2:$B$315,$A23) -> 5 | D23: =COUNTIFS(Entreprises!$A$2:$A$315,D$3,Entreprises!$B$2:$B$315,$A23) -> 4 | E23: =SUM(B23:D23) -> 14
A24: Total | B24: =SUM(B4:B23) -> 127 | C24: =SUM(C4:C23) -> 99 | D24: =SUM(D4:D23) -> 88 | E24: =SUM(E4:E23) -> 314
A26: Notes & méthode
A27: • Source : Google Maps / Google Places (recherche par catégorie et par ville) ; données collectées le 21/09/2026.
A28: • Ce fichier est un ÉCHANTILLON représentatif (20 secteurs × 3 villes), pas une liste exhaustive : des dizaines de milliers d'entreprises sont référencées sur Google Maps dans ces villes.
A29: • Prix : Google Maps n'affiche pas les tarifs. Les montants indiqués proviennent d'avis clients (à vérifier) ; sinon le niveau de prix Google ($ à $$$$) est repris quand il existe.
A30: • Avis : note et nombre d'avis proviennent de Google ; la synthèse est une reformulation des avis récents affichés (pas une citation).
A31: • Lien : ouvre la fiche de l'établissement sur Google Maps (coordonnées GPS + identifiant du lieu). Le bouton « Site web » de la fiche Maps, quand il existe, mène au site officiel.
A32: • Site web : la colonne contient un lien de recherche Google (nom + ville) vers le site officiel ; les URL n'ont pas pu être extraites automatiquement de façon fiable. Beaucoup de PME locales n'ont qu'une page Facebook/WhatsApp, sans site.
A33: • Certaines fiches ont peu ou pas d'avis, ou des horaires/numéros à confirmer : vérifiez avant de vous déplacer.
